<Properties StartupConfiguration="{5E654687-AB6C-4253-697D-CD95BF6C5691}|">
  <MonoDevelop.Ide.Workbench ActiveDocument="Assets/Scripts/Trackables.cs">
    <Files>
      <File FileName="Assets/Scripts/StateChanger.cs" Line="30" Column="68" />
      <File FileName="Assets/Scripts/Trackables.cs" Line="1" Column="1" />
    </Files>
    <Pads>
      <Pad Id="ProjectPad">
        <State name="__root__">
          <Node name="Projeto" expanded="True">
            <Node name="Assets" expanded="True">
              <Node name="Scripts" expanded="True">
                <Node name="Trackables.cs" selected="True" />
              </Node>
            </Node>
          </Node>
        </State>
      </Pad>
    </Pads>
  </MonoDevelop.Ide.Workbench>
  <MonoDevelop.Ide.DebuggingService.PinnedWatches />
  <MonoDevelop.Ide.Workspace ActiveConfiguration="Debug" />
  <MonoDevelop.Ide.ItemProperties.Assembly-CSharp PreferredExecutionTarget="3578d970-51b8-43b1-8098-fc8941edbd91" />
  <MonoDevelop.Ide.DebuggingService.Breakpoints>
    <BreakpointStore />
  </MonoDevelop.Ide.DebuggingService.Breakpoints>
  <MultiItemStartupConfigurations />
</Properties>